ipuppy_notebooks/__init__.py
ipuppy_notebooks/conversation_history.py
ipuppy_notebooks/frontend_operations.py
ipuppy_notebooks/main.py
ipuppy_notebooks/py_notebook.py
ipuppy_notebooks/socket_handlers.py
ipuppy_notebooks/test_frontend_operations.py
ipuppy_notebooks/agent/__init__.py
ipuppy_notebooks/agent/agent.py
ipuppy_notebooks/agent/prompts.py
ipuppy_notebooks/agent/tools.py
ipuppy_notebooks/compiled_ui/index.html
ipuppy_notebooks/compiled_ui/puppy.svg
ipuppy_notebooks/compiled_ui/vite.svg
ipuppy_notebooks/compiled_ui/assets/index-CRSv9aMb.js
ipuppy_notebooks/compiled_ui/assets/index-DX9htSWo.css
ipuppy_notebooks/compiled_ui/assets/tabHandler-B8LyEOYf.js
ipuppy_notebooks/kernels/__init__.py
ipuppy_notebooks/kernels/executor.py
ipuppy_notebooks/kernels/manager.py
LICENSE
README.md
ipuppy_notebooks-0.1.17.dist-info/METADATA
ipuppy_notebooks-0.1.17.dist-info/WHEEL
ipuppy_notebooks-0.1.17.dist-info/entry_points.txt
ipuppy_notebooks-0.1.17.dist-info/licenses/LICENSE
ipuppy_notebooks-0.1.17.dist-info/RECORD
