Metadata-Version: 2.4
Name: ipuppy-notebooks
Version: 0.1.17
Summary: 🐶 Agentic AI-Empowered Data Science Notebooks - A revolutionary notebook environment combining Jupyter-style computing with autonomous AI assistance
Project-URL: Homepage, https://github.com/your-username/iPuppy-Notebooks
Project-URL: Repository, https://github.com/your-username/iPuppy-Notebooks
Project-URL: Documentation, https://github.com/your-username/iPuppy-Notebooks#readme
Project-URL: Bug Tracker, https://github.com/your-username/iPuppy-Notebooks/issues
Author-email: Michael Pfaffenberger <michael@example.com>
License: MIT
License-File: LICENSE
Keywords: agent,ai,data-science,fastapi,jupyter,notebook,react
Classifier: Development Status :: 4 - Beta
Classifier: Intended Audience :: Developers
Classifier: Intended Audience :: Science/Research
Classifier: License :: OSI Approved :: MIT License
Classifier: Programming Language :: Python :: 3
Classifier: Programming Language :: Python :: 3.10
Classifier: Programming Language :: Python :: 3.11
Classifier: Topic :: Scientific/Engineering
Classifier: Topic :: Software Development :: Libraries :: Python Modules
Requires-Python: >=3.10
Requires-Dist: aiofiles>=0.7.0
Requires-Dist: code-puppy>=0.0.140
Requires-Dist: fastapi>=0.68.0
Requires-Dist: ipykernel>=6.0.0
Requires-Dist: jinja2>=3.0.0
Requires-Dist: jupyter-client>=7.0.0
Requires-Dist: matplotlib>=3.10.5
Requires-Dist: notebook>=6.4.0
Requires-Dist: numpy>=2.2.6
Requires-Dist: plotly>=6.2.0
Requires-Dist: pydantic-ai>=0.0.1
Requires-Dist: python-multipart>=0.0.5
Requires-Dist: python-socketio>=5.13.0
Requires-Dist: seaborn>=0.13.2
Requires-Dist: uvicorn>=0.15.0
Requires-Dist: websockets>=10.0
